{"cameraMode":{"drawMode":0,"name":"Shaded","section":"Shading Mode"},"sceneLighting":false,"audioPlay":false,"sceneViewState":{"showFog":true,"showMaterialUpdate":false,"showSkybox":false,"showFlares":true,"showImageEffects":true,"showParticleSystems":true},"in2DMode":false,"pivot":{"x":1.7000715732574463,"y":4.7804765701293949,"z":-2.321624517440796},"rotation":{"x":-0.4893251955509186,"y":-0.0564597062766552,"z":0.03181018680334091,"w":-0.8698745369911194},"size":3.6129415035247804,"orthographic":false}